[
  {
    "nom": "Arachitik la Souffreteuse",
    "etape": 20,
    "zone": "Astrub",
    "sous-zone": "Souterrains d'Astrub",
    "imgURL": "https://res.cloudinary.com/dinaj1mwf/image/upload/v1683914543/arakne_malade_pdnype.jpg"
  },
  {
    "nom": "Araknay la Galopante",
    "etape": 20,
    "zone": "Astrub",
    "sous-zone": "Egouts d'Astrub",
    "imgURL": "https://res.cloudinary.com/dinaj1mwf/image/upload/v1683914680/arakne_cfcaby.jpg"
  },
  {
    "nom": "Arakule la Revancharde",
    "etape": 20,
    "zone": "Amakna",
    "sous-zone": "Forêt maléfique",
    "imgURL": "https://res.cloudinary.com/dinaj1mwf/image/upload/v1683914700/arakne_agressive_v5p1ru.jpg"
  },
  {
    "nom": "Boudalf le Blanc",
    "etape": 20,
    "zone": "Amakna",
    "sous-zone": "Coin des bouftous",
    "imgURL": "https://res.cloudinary.com/dinaj1mwf/image/upload/v1683914735/boufton_blanc_rnxijs.jpg"
  },
  {
    "nom": "Boulgourvil le Lointain",
    "etape": 20,
    "zone": "Amakna",
    "sous-zone": "Coin des bouftous",
    "imgURL": "https://res.cloudinary.com/dinaj1mwf/image/upload/v1683914754/boufton_noir_uqrtfs.jpg"
  },
  {
    "nom": "Chamchie le Difficile",
    "etape": 20,
    "zone": "Amakna",
    "sous-zone": "Coin des bouftous",
    "imgURL": "https://res.cloudinary.com/dinaj1mwf/image/upload/v1683915258/champ_champ_flqfur.jpg"
  },
  {
    "nom": "Craraboss le Féérique",
    "etape": 20,
    "zone": "Baie de Sufokia",
    "sous-zone": "Rivage sufokien",
    "imgURL": "https://res.cloudinary.com/dinaj1mwf/image/upload/v1683915283/crabe_s2dsbq.jpg"
  },
  {
    "nom": "Larvonika l'Instrument",
    "etape": 20,
    "zone": "Amakna",
    "sous-zone": "Port de Madrestam",
    "imgURL": "https://res.cloudinary.com/dinaj1mwf/image/upload/v1683915324/larve_bleue_fldqor.jpg"
  },
  {
    "nom": "Mosketère le Dévoué",
    "etape": 20,
    "zone": "Amakna",
    "sous-zone": "Bord de la forêt maléfique",
    "imgURL": "https://res.cloudinary.com/dinaj1mwf/image/upload/v1683923082/moskito_rvljni.jpg"
  },
  {
    "nom": "Pioufe la Maquillée",
    "etape": 20,
    "zone": "Baie de Sufokia",
    "sous-zone": "Sufokia",
    "imgURL": "https://res.cloudinary.com/dinaj1mwf/image/upload/v1683923126/piou_rose_a8foxv.jpg"
  },
  {
    "nom": "Pioukas la Plante",
    "etape": 20,
    "zone": "Baie de Sufokia",
    "sous-zone": "Sufokia",
    "imgURL": "https://res.cloudinary.com/dinaj1mwf/image/upload/v1683923162/piou_vert_s6jr5o.jpg"
  },
  {
    "nom": "Pioulbrineur le Mercenaire",
    "etape": 20,
    "zone": "Baie de Sufokia",
    "sous-zone": "Sufokia",
    "imgURL": "https://res.cloudinary.com/dinaj1mwf/image/upload/v1683923182/piou_jaune_jwmfaw.jpg"
  },
  {
    "nom": "Pioulette la Coquine",
    "etape": 20,
    "zone": "Astrub",
    "sous-zone": "Cité d'Astrub",
    "imgURL": "https://res.cloudinary.com/dinaj1mwf/image/upload/v1683923206/piou_rouge_wybru6.jpg"
  },
  {
    "nom": "Pioussokrim le Délétère",
    "etape": 20,
    "zone": "Baie de Sufokia",
    "sous-zone": "Sufokia",
    "imgURL": "https://res.cloudinary.com/dinaj1mwf/image/upload/v1683923220/piou_violet_ohbjhp.jpg"
  },
  {
    "nom": "Pioustone le Problème",
    "etape": 20,
    "zone": "Baie de Sufokia",
    "sous-zone": "Sufokia",
    "imgURL": "https://res.cloudinary.com/dinaj1mwf/image/upload/v1683923243/piou_bleu_elsdhz.jpg"
  },
  {
    "nom": "Pissdane l'Insipide",
    "etape": 20,
    "zone": "Bonta",
    "sous-zone": "Rive iridescentes",
    "imgURL": "https://res.cloudinary.com/dinaj1mwf/image/upload/v1683923263/pissenlit_diabolique_x8prml.jpg"
  },
  {
    "nom": "Sourizoto le Collant",
    "etape": 20,
    "zone": "Amakna",
    "sous-zone": "Cryptes du cimetière",
    "imgURL": "https://res.cloudinary.com/dinaj1mwf/image/upload/v1683923295/souris_grise_w6koc9.jpg"
  },
  {
    "nom": "Tofuldebeu l'Explosif",
    "etape": 20,
    "zone": "Amakna",
    "sous-zone": "Champ des Ingalsse",
    "imgURL": "https://res.cloudinary.com/dinaj1mwf/image/upload/v1683923348/tofu_gac9av.jpg"
  },
  {
    "nom": "Tofumanchou l'Empereur",
    "etape": 20,
    "zone": "Amakna",
    "sous-zone": "Forêt maléfique",
    "imgURL": "https://res.cloudinary.com/dinaj1mwf/image/upload/v1683923371/tofu_malefique_xdhvnv.jpg"
  },
  {
    "nom": "Tofurapin le Pétri",
    "etape": 20,
    "zone": "Astrub",
    "sous-zone": "Souterrains d'Astrub",
    "imgURL": "https://res.cloudinary.com/dinaj1mwf/image/upload/v1683923389/tofu_malade_e7xnov.jpg"
  },
  {
    "nom": "Bandapar l'Exclu",
    "etape": 21,
    "zone": "Amakna",
    "sous-zone": "Passage vers Brâkmar",
    "imgURL": "https://res.cloudinary.com/dinaj1mwf/image/upload/v1683923477/bandit_manchot_dakhnz.jpg"
  },
  {
    "nom": "Bandson le Tonitruant",
    "etape": 21,
    "zone": "Amakna",
    "sous-zone": "Territoire des Bandits",
    "imgURL": "https://res.cloudinary.com/dinaj1mwf/image/upload/v1683923490/bandit_du_clan_des_roublards_pbdmcd.jpg"
  },
  {
    "nom": "Boudur le Raide",
    "etape": 21,
    "zone": "Amakna",
    "sous-zone": "Territoire des Bandits",
    "imgURL": "https://res.cloudinary.com/dinaj1mwf/image/upload/v1683923508/boulanger_sombre_nll6d8.jpg"
  },
  {
    "nom": "Boufdégou le Refoulant",
    "etape": 21,
    "zone": "Amakna",
    "sous-zone": "Coin des bouftous",
    "imgURL": "https://res.cloudinary.com/dinaj1mwf/image/upload/v1683923526/bouftou_owkrsn.jpg"
  },
  {
    "nom": "Gelanal le Huileux",
    "etape": 21,
    "zone": "Amakna",
    "sous-zone": "Péninsule des gelées",
    "imgURL": "https://res.cloudinary.com/dinaj1mwf/image/upload/v1683923546/gelee_bleue_kf1wzt.jpg"
  },
  {
    "nom": "Geloliaine l'Aérien",
    "etape": 21,
    "zone": "Amakna",
    "sous-zone": "Péninsule des gelées",
    "imgURL": "https://res.cloudinary.com/dinaj1mwf/image/upload/v1683923563/gelee_menthe_w176ej.jpg"
  },
  {
    "nom": "Gobstiniais le Têtu",
    "etape": 21,
    "zone": "Amakna",
    "sous-zone": "Montagne basse des Craqueleurs",
    "imgURL": "https://res.cloudinary.com/dinaj1mwf/image/upload/v1683923593/gobelin_myiulv.jpg"
  },
  {
    "nom": "Kolforthe l'Indécollable",
    "etape": 21,
    "zone": "Landes de Sidimote",
    "sous-zone": "Désolation de Sidimote",
    "imgURL": "https://res.cloudinary.com/dinaj1mwf/image/upload/v1683923624/kolerat_ytwmxj.jpg"
  },
  {
    "nom": "Kwoanneur le Frimeur",
    "etape": 21,
    "zone": "Amakna",
    "sous-zone": "Cimetière d'Amakna",
    "imgURL": "https://res.cloudinary.com/dinaj1mwf/image/upload/v1683923684/kwoan_vvjo4u.jpg"
  },
  {
    "nom": "Larchimaide la Poussée",
    "etape": 21,
    "zone": "Amakna",
    "sous-zone": "Port de Madrestam",
    "imgURL": "https://res.cloudinary.com/dinaj1mwf/image/upload/v1683923770/larve_verte_gdyiqe.jpg"
  },
  {
    "nom": "Larvapstrè le Subjectif",
    "etape": 21,
    "zone": "Amakna",
    "sous-zone": "Port de Madrestam",
    "imgURL": "https://res.cloudinary.com/dinaj1mwf/image/upload/v1683923880/larve_orange_fx0hqu.jpg"
  },
  {
    "nom": "Nodkoku le Trahi",
    "etape": 21,
    "zone": "Île de Moon",
    "sous-zone": "Cimetière d'Amakna",
    "imgURL": "https://res.cloudinary.com/dinaj1mwf/image/upload/v1683923901/nodkoko_bqgbgv.jpg"
  },
  {
    "nom": "Roz la Magicienne",
    "etape": 21,
    "zone": "Bonta",
    "sous-zone": "Rive iridescentes",
    "imgURL": "https://res.cloudinary.com/dinaj1mwf/image/upload/v1683923917/rose_demoniaque_xfj94p.jpg"
  },
  {
    "nom": "Serpistol l'Illustre",
    "etape": 21,
    "zone": "Plaines de Cania",
    "sous-zone": "Champs de Cania",
    "imgURL": "https://res.cloudinary.com/dinaj1mwf/image/upload/v1683923940/serpentin_vdbloe.jpg"
  },
  {
    "nom": "Tikosto le Mousse",
    "etape": 21,
    "zone": "Île de Moon",
    "sous-zone": "Plage de la Tortue",
    "imgURL": "https://res.cloudinary.com/dinaj1mwf/image/upload/v1683923967/tikokoko_uu2z05.jpg"
  },
  {
    "nom": "Tiwa'Missou le Gateux",
    "etape": 21,
    "zone": "Île des Wabbits",
    "sous-zone": "Île de la Cawotte",
    "imgURL": "https://res.cloudinary.com/dinaj1mwf/image/upload/v1683924065/black_tiwabbit_zxry0g.jpg"
  },
  {
    "nom": "Tiwalpé le Dévêtu",
    "etape": 21,
    "zone": "Île des Wabbits",
    "sous-zone": "Île de la Cawotte",
    "imgURL": "https://res.cloudinary.com/dinaj1mwf/image/upload/v1683924109/tiwabbit_nzczri.jpg"
  },
  {
    "nom": "Tiwoflan le Lâche",
    "etape": 21,
    "zone": "Île des Wabbits",
    "sous-zone": "Île de la Cawotte",
    "imgURL": "https://res.cloudinary.com/dinaj1mwf/image/upload/v1683924128/tiwabbit_kiafin_xe0rll.jpg"
  },
  {
    "nom": "Tour le Vice",
    "etape": 21,
    "zone": "Bonta",
    "sous-zone": "Rive iridescentes",
    "imgURL": "https://res.cloudinary.com/dinaj1mwf/image/upload/v1683924168/tournesol_sauvage_fykav4.jpg"
  },
  {
    "nom": "Trukul le Lent",
    "etape": 21,
    "zone": "Île de Moon",
    "sous-zone": "Jungle interdite",
    "imgURL": "https://res.cloudinary.com/dinaj1mwf/image/upload/v1683924269/trukikol_unu6k5.jpg"
  },
  {
    "nom": "Bi le Partageur",
    "etape": 22,
    "zone": "Plaines de Cania",
    "sous-zone": "Lac de Cania",
    "imgURL": "https://res.cloudinary.com/dinaj1mwf/image/upload/v1683924429/biblop_griotte_btj529.jpg"
  },
  {
    "nom": "Bilvoezé le Bonimenteur",
    "etape": 22,
    "zone": "Plaines de Cania",
    "sous-zone": "Lac de Cania",
    "imgURL": "https://res.cloudinary.com/dinaj1mwf/image/upload/v1683924432/biblop_coco_z734ve.jpg"
  },
  {
    "nom": "Bistou le Quêteur",
    "etape": 22,
    "zone": "Plaines de Cania",
    "sous-zone": "Lac de Cania",
    "imgURL": "https://res.cloudinary.com/dinaj1mwf/image/upload/v1683924435/biblop_indigo_h1xvdn.jpg"
  },
  {
    "nom": "Bistou le Rieur",
    "etape": 22,
    "zone": "Plaines de Cania",
    "sous-zone": "Lac de Cania",
    "imgURL": "https://res.cloudinary.com/dinaj1mwf/image/upload/v1683924439/biblop_reinette_hvuswo.jpg"
  },
  {
    "nom": "Boostif l'Affamé",
    "etape": 22,
    "zone": "Montagnes des Koalaks",
    "sous-zone": "Marécages nauséabonds",
    "imgURL": "https://res.cloudinary.com/dinaj1mwf/image/upload/v1683924446/boo_mzxikb.jpg"
  },
  {
    "nom": "Bouflet le Puéril",
    "etape": 22,
    "zone": "Amakna",
    "sous-zone": "Coin des bouftous",
    "imgURL": "https://res.cloudinary.com/dinaj1mwf/image/upload/v1683924649/chef_de_guerre_bouftou_jsafon.jpg"
  },
  {
    "nom": "Champayr le Disjoncté",
    "etape": 22,
    "zone": "Amakna",
    "sous-zone": "Clairière de Brouce Boulgoure",
    "imgURL": "https://res.cloudinary.com/dinaj1mwf/image/upload/v1683924667/champa_vert_lc8cmi.jpg"
  },
  {
    "nom": "Chevaustine le Reconstruit",
    "etape": 22,
    "zone": "Amakna",
    "sous-zone": "Montagne basse des Craqueleurs",
    "imgURL": "https://res.cloudinary.com/dinaj1mwf/image/upload/v1683924712/chevaucheur_de_karne_p1ftyn.jpg"
  },
  {
    "nom": "Chonstip la Passagère",
    "etape": 22,
    "zone": "Plaines de Cania",
    "sous-zone": "Plaines des Porkass",
    "imgURL": "https://res.cloudinary.com/dinaj1mwf/image/upload/v1683924755/cochon_de_lait_pg8wcb.jpg"
  },
  {
    "nom": "Cromikay le Néophyte",
    "etape": 22,
    "zone": "Landes de Sidimote",
    "sous-zone": "Désolation de Sidimote",
    "imgURL": "https://res.cloudinary.com/dinaj1mwf/image/upload/v1683924808/croc_gland_om2hbe.jpg"
  },
  {
    "nom": "Étoilette la Bouchée",
    "etape": 22,
    "zone": "Baie de Sufokia",
    "sous-zone": "Rivage sufokien",
    "imgURL": "https://res.cloudinary.com/dinaj1mwf/image/upload/v1683924832/etoile_de_la_mer_dasse_rmoatx.jpg"
  },
  {
    "nom": "Milipussien le Géant",
    "etape": 22,
    "zone": "Astrub",
    "sous-zone": "Egouts d'Astrub",
    "imgURL": "https://res.cloudinary.com/dinaj1mwf/image/upload/v1683924881/milirat_degoutant_malade_trezsa.jpg"
  },
  {
    "nom": "Porfavor le Quémandeur",
    "etape": 22,
    "zone": "Plaines de Cania",
    "sous-zone": "Plaines des Porkass",
    "imgURL": "https://res.cloudinary.com/dinaj1mwf/image/upload/v1683924905/berger_porkass_zh1y6h.jpg"
  },
  {
    "nom": "Preskapwal le Tendancieux",
    "etape": 22,
    "zone": "Amakna",
    "sous-zone": "Forêt d'Amakna",
    "imgURL": "https://res.cloudinary.com/dinaj1mwf/image/upload/v1683924934/prespic_uwul9a.jpg"
  },
  {
    "nom": "Robiolego l'Assemblé",
    "etape": 22,
    "zone": "Plaines de Cania",
    "sous-zone": "Massif de Cania",
    "imgURL": "https://res.cloudinary.com/dinaj1mwf/image/upload/v1683924954/robionicle_f7jynf.png"
  },
  {
    "nom": "Sangria le Fruité",
    "etape": 22,
    "zone": "Amakna",
    "sous-zone": "Forêt d'Amakna",
    "imgURL": "https://res.cloudinary.com/dinaj1mwf/image/upload/v1683924986/sanglier_ttykvs.jpg"
  },
  {
    "nom": "Tortenssia la Fleurie",
    "etape": 22,
    "zone": "Île de Moon",
    "sous-zone": "Plage de la Tortue",
    "imgURL": "https://res.cloudinary.com/dinaj1mwf/image/upload/v1683925055/tortue_bleue_mpriyx.jpg"
  },
  {
    "nom": "Torthur la Lutte",
    "etape": 22,
    "zone": "Île de Moon",
    "sous-zone": "Plage de la Tortue",
    "imgURL": "https://res.cloudinary.com/dinaj1mwf/image/upload/v1683925068/tortue_jaune_sre9y3.jpg"
  },
  {
    "nom": "Vampunor le Glacial",
    "etape": 22,
    "zone": "Amakna",
    "sous-zone": "Cryptes du cimetière",
    "imgURL": "https://res.cloudinary.com/dinaj1mwf/image/upload/v1683925162/vampire_zkx9xm.jpg"
  },
  {
    "nom": "Wabbitud le Constant",
    "etape": 22,
    "zone": "Île des Wabbits",
    "sous-zone": "Île de la Cawotte",
    "imgURL": "https://res.cloudinary.com/dinaj1mwf/image/upload/v1683925163/wabbit_a86d9e.jpg"
  },
  {
    "nom": "Bambouské le Camouflé",
    "etape": 23,
    "zone": "Île de Pandala",
    "sous-zone": "Plantala",
    "imgURL": "https://res.cloudinary.com/dinaj1mwf/image/upload/v1683925164/bambouto_bqgjhy.jpg"
  },
  {
    "nom": "Barchwork le Multicolore",
    "etape": 23,
    "zone": "Amakna",
    "sous-zone": "Forêt maléfique",
    "imgURL": "https://res.cloudinary.com/dinaj1mwf/image/upload/v1683925166/bwork_archer_fqnk7v.jpg"
  },
  {
    "nom": "Bwormage le Respectueux",
    "etape": 23,
    "zone": "Amakna",
    "sous-zone": "Forêt maléfique",
    "imgURL": "https://res.cloudinary.com/dinaj1mwf/image/upload/v1683925166/bwork_mage_vjwdhi.jpg"
  },
  {
    "nom": "Corpat le Vampire",
    "etape": 23,
    "zone": "Plaines de Cania",
    "sous-zone": "Pénates du Corbac",
    "imgURL": "https://res.cloudinary.com/dinaj1mwf/image/upload/v1683925169/corbac_tipxjf.jpg"
  },
  {
    "nom": "Crognan le Barbare",
    "etape": 23,
    "zone": "Landes de Sidimote",
    "sous-zone": "Désolation de Sidimote",
    "imgURL": "https://res.cloudinary.com/dinaj1mwf/image/upload/v1683925170/crowneille_maj9j7.jpg"
  },
  {
    "nom": "Fourapin le Chaud",
    "etape": 23,
    "zone": "Île de Moon",
    "sous-zone": "Jungle interdite",
    "imgURL": "https://res.cloudinary.com/dinaj1mwf/image/upload/v1683925173/fourbasse_dvoe9x.jpg"
  },
  {
    "nom": "Maître Amboat le Moqueur",
    "etape": 23,
    "zone": "Amakna",
    "sous-zone": "Cryptes du cimetière",
    "imgURL": "https://res.cloudinary.com/dinaj1mwf/image/upload/v1683925178/maitre_vampire_nofxba.jpg"
  },
  {
    "nom": "Milipatte la Griffe",
    "etape": 23,
    "zone": "Amakna",
    "sous-zone": "Forêt d'Amakna",
    "imgURL": "https://res.cloudinary.com/dinaj1mwf/image/upload/v1683925179/milimulou_wgi32q.jpg"
  },
  {
    "nom": "Minoskour le Sauveur",
    "etape": 23,
    "zone": "Île du Minotoror",
    "sous-zone": "Île du Minotoror",
    "imgURL": "https://res.cloudinary.com/dinaj1mwf/image/upload/v1683925179/minoskito_xuigu1.jpg"
  },
  {
    "nom": "Minsinistre l'Elu",
    "etape": 23,
    "zone": "Amakna",
    "sous-zone": "Territoire des Bandits",
    "imgURL": "https://res.cloudinary.com/dinaj1mwf/image/upload/v1683925179/mineur_sombre_kycgzl.jpg"
  },
  {
    "nom": "Neufedur le Flottant",
    "etape": 23,
    "zone": "Amakna",
    "sous-zone": "Forêt maléfique",
    "imgURL": "https://res.cloudinary.com/dinaj1mwf/image/upload/v1683925157/noeul_ozma2o.jpg"
  },
  {
    "nom": "Pichakoté le Dégoûtant",
    "etape": 23,
    "zone": "Astrub",
    "sous-zone": "Calanques d'Astrub",
    "imgURL": "https://res.cloudinary.com/dinaj1mwf/image/upload/v1683925158/pichon_vert_dgcfm4.jpg"
  },
  {
    "nom": "Pichdourse le Puissant",
    "etape": 23,
    "zone": "Astrub",
    "sous-zone": "Calanques d'Astrub",
    "imgURL": "https://res.cloudinary.com/dinaj1mwf/image/upload/v1683925158/pichon_bleu_kjmrhd.jpg"
  },
  {
    "nom": "Pichduitre le Totem",
    "etape": 23,
    "zone": "Astrub",
    "sous-zone": "Calanques d'Astrub",
    "imgURL": "https://res.cloudinary.com/dinaj1mwf/image/upload/v1683925158/pichon_blanc_lk85pf.jpg"
  },
  {
    "nom": "Pichtoire l'Erudit",
    "etape": 23,
    "zone": "Astrub",
    "sous-zone": "Calanques d'Astrub",
    "imgURL": "https://res.cloudinary.com/dinaj1mwf/image/upload/v1683925158/pichon_orange_a7rcvv.jpg"
  },
  {
    "nom": "Robocoop l'Échangé",
    "etape": 23,
    "zone": "Plaines de Cania",
    "sous-zone": "Massif de Cania",
    "imgURL": "https://res.cloudinary.com/dinaj1mwf/image/upload/v1683925159/robot-fleau_qfd2fu.png"
  },
  {
    "nom": "Rostensyl la Cuisinière",
    "etape": 23,
    "zone": "Bonta",
    "sous-zone": "Rive iridescentes",
    "imgURL": "https://res.cloudinary.com/dinaj1mwf/image/upload/v1683925160/rose_obscure_nmhuc2.jpg"
  },
  {
    "nom": "Tortilleur le Coulé",
    "etape": 23,
    "zone": "Île de Moon",
    "sous-zone": "Plage de la Tortue",
    "imgURL": "https://res.cloudinary.com/dinaj1mwf/image/upload/v1683925162/tortue_verte_jc8vff.jpg"
  },
  {
    "nom": "Tortorak le Cornu",
    "etape": 23,
    "zone": "Île de Moon",
    "sous-zone": "Plage de la Tortue",
    "imgURL": "https://res.cloudinary.com/dinaj1mwf/image/upload/v1683925162/tortue_rouge_wpiy3n.jpg"
  },
  {
    "nom": "Wagnagnah le Sanglant",
    "etape": 23,
    "zone": "Île des Wabbits",
    "sous-zone": "Île de la Cawotte",
    "imgURL": "https://res.cloudinary.com/dinaj1mwf/image/upload/v1683925165/black_wabbit_psl0yj.jpg"
  },
  {
    "nom": "Abrakroc l'Edenté",
    "etape": 24,
    "zone": "Forêt des Abraknydes",
    "sous-zone": "Orée de la forêt des Abraknydes",
    "imgURL": "https://res.cloudinary.com/dinaj1mwf/image/upload/v1683925164/abraknyde_venerable_z4tn2u.jpg"
  },
  {
    "nom": "Bworkasse le Dégoûtant",
    "etape": 24,
    "zone": "Amakna",
    "sous-zone": "Forêt maléfique",
    "imgURL": "https://res.cloudinary.com/dinaj1mwf/image/upload/v1683925166/bwork_quqael.jpg"
  },
  {
    "nom": "Chafalfer l'Optimiste",
    "etape": 24,
    "zone": "Amakna",
    "sous-zone": "Forêt maléfique",
    "imgURL": "https://res.cloudinary.com/dinaj1mwf/image/upload/v1683925167/chafer_invisible_hi4opb.jpg"
  },
  {
    "nom": "Chamdblé le Cultivé",
    "etape": 24,
    "zone": "Amakna",
    "sous-zone": "Clairière de Brouce Boulgoure",
    "imgURL": "https://res.cloudinary.com/dinaj1mwf/image/upload/v1683925168/champa_rouge_jc8efc.jpg"
  },
  {
    "nom": "Chamflay le Ballonné",
    "etape": 24,
    "zone": "Amakna",
    "sous-zone": "Clairière de Brouce Boulgoure",
    "imgURL": "https://res.cloudinary.com/dinaj1mwf/image/upload/v1683925168/champa_marron_wfblhl.jpg"
  },
  {
    "nom": "Champayt l'Odorant",
    "etape": 24,
    "zone": "Amakna",
    "sous-zone": "Clairière de Brouce Boulgoure",
    "imgURL": "https://res.cloudinary.com/dinaj1mwf/image/upload/v1683925167/champa_bleu_qeq3wx.jpg"
  },
  {
    "nom": "Crakmitaine le Faucheur",
    "etape": 24,
    "zone": "Amakna",
    "sous-zone": "Montagne des Craqueleurs",
    "imgURL": "https://res.cloudinary.com/dinaj1mwf/image/upload/v1683925169/craqueleur_ogphmz.jpg"
  },
  {
    "nom": "Craquetuss le Piquant",
    "etape": 24,
    "zone": "Amakna",
    "sous-zone": "Montagne des Craqueleurs",
    "imgURL": "https://res.cloudinary.com/dinaj1mwf/image/upload/v1683925169/craqueboule_lyemmv.jpg"
  },
  {
    "nom": "Draglida la Disparue",
    "etape": 24,
    "zone": "Montagnes des Koalaks",
    "sous-zone": "Territoire des Dragodindes Sauvages",
    "imgURL": "https://res.cloudinary.com/dinaj1mwf/image/upload/v1683925170/dragodinde_amande_sauvage_gxlb0w.jpg"
  },
  {
    "nom": "Garsim le Mort",
    "etape": 24,
    "zone": "Astrub",
    "sous-zone": "Cimetière d'Astrub",
    "imgURL": "https://res.cloudinary.com/dinaj1mwf/image/upload/v1683925173/gargrouille_utl6nt.jpg"
  },
  {
    "nom": "Gelaviv le Glaçon",
    "etape": 24,
    "zone": "Amakna",
    "sous-zone": "Péninsule des gelées",
    "imgURL": "https://res.cloudinary.com/dinaj1mwf/image/upload/v1683925173/gelee_fraise_kh5zoo.jpg"
  },
  {
    "nom": "Krapahut le Randonneur",
    "etape": 24,
    "zone": "Île du Minotoror",
    "sous-zone": "Île du Minotoror",
    "imgURL": "https://res.cloudinary.com/dinaj1mwf/image/upload/v1683925176/kramelehon_uwcypq.jpg"
  },
  {
    "nom": "Mallopiée l'Épineuse",
    "etape": 24,
    "zone": "Plaines de Cania",
    "sous-zone": "Massif de Cania",
    "imgURL": "https://res.cloudinary.com/dinaj1mwf/image/upload/v1683925178/malle-outillee_igqwnm.png"
  },
  {
    "nom": "Mandalo l'Aqueuse",
    "etape": 24,
    "zone": "Île du Minotoror",
    "sous-zone": "Île du Minotoror",
    "imgURL": "https://res.cloudinary.com/dinaj1mwf/image/upload/v1683925178/mandrine_va9hso.jpg"
  },
  {
    "nom": "Ribibi le Cher",
    "etape": 24,
    "zone": "Amakna",
    "sous-zone": "Forêt maléfique",
    "imgURL": "https://res.cloudinary.com/dinaj1mwf/image/upload/v1683925159/rib_zsozzb.jpg"
  },
  {
    "nom": "Scapé l'Epée",
    "etape": 24,
    "zone": "Amakna",
    "sous-zone": "Plaine des Scarafeuilles",
    "imgURL": "https://res.cloudinary.com/dinaj1mwf/image/upload/v1683925160/scarafeuille_blanc_ly01qp.jpg"
  },
  {
    "nom": "Scaramel le Fondant",
    "etape": 24,
    "zone": "Amakna",
    "sous-zone": "Plaine des Scarafeuilles",
    "imgURL": "https://res.cloudinary.com/dinaj1mwf/image/upload/v1683925161/scarafeuille_vert_d4cr1t.jpg"
  },
  {
    "nom": "Scarfayss le Balafré",
    "etape": 24,
    "zone": "Amakna",
    "sous-zone": "Plaine des Scarafeuilles",
    "imgURL": "https://res.cloudinary.com/dinaj1mwf/image/upload/v1683925160/scarafeuille_bleu_ph8u6x.jpg"
  },
  {
    "nom": "Scarouarze l'Epopée",
    "etape": 24,
    "zone": "Amakna",
    "sous-zone": "Plaine des Scarafeuilles",
    "imgURL": "https://res.cloudinary.com/dinaj1mwf/image/upload/v1683925160/scarafeuille_rouge_khemcw.jpg"
  },
  {
    "nom": "Watdogue le Bien Nommé",
    "etape": 24,
    "zone": "Île des Wabbits",
    "sous-zone": "Îlot des Tombeaux",
    "imgURL": "https://res.cloudinary.com/dinaj1mwf/image/upload/v1683925163/wabbit_squelette_echm8h.jpg"
  },
  {
    "nom": "Abrakadnuzar",
    "etape": 25,
    "zone": "Forêt des Abraknydes",
    "sous-zone": "Orée de la forêt des Abraknydes",
    "imgURL": "https://res.cloudinary.com/dinaj1mwf/image/upload/v1683925163/abrakne_zwod89.jpg"
  },
  {
    "nom": "Blof l'Apathique",
    "etape": 25,
    "zone": "Plaines de Cania",
    "sous-zone": "Lac de Cania",
    "imgURL": "https://res.cloudinary.com/dinaj1mwf/image/upload/v1683925165/blop_reinette_ky6pvc.jpg"
  },
  {
    "nom": "Bloporte le Veule",
    "etape": 25,
    "zone": "Plaines de Cania",
    "sous-zone": "Lac de Cania",
    "imgURL": "https://res.cloudinary.com/dinaj1mwf/image/upload/v1683925165/blop_indigo_na4srb.jpg"
  },
  {
    "nom": "Blordur l'Infect",
    "etape": 25,
    "zone": "Plaines de Cania",
    "sous-zone": "Lac de Cania",
    "imgURL": "https://res.cloudinary.com/dinaj1mwf/image/upload/v1683925165/blop_griotte_dw8zbq.jpg"
  },
  {
    "nom": "Blorie l'Assourdissante",
    "etape": 25,
    "zone": "Plaines de Cania",
    "sous-zone": "Lac de Cania",
    "imgURL": "https://res.cloudinary.com/dinaj1mwf/image/upload/v1683925165/blop_coco_dadjlg.jpg"
  },
  {
    "nom": "Boombata le Garde",
    "etape": 25,
    "zone": "Île de Moon",
    "sous-zone": "Chemin du Crâne",
    "imgURL": "https://res.cloudinary.com/dinaj1mwf/image/upload/v1683925165/boomba_ldloup.jpg"
  },
  {
    "nom": "Bulsavon le Gonflé",
    "etape": 25,
    "zone": "Île de Pandala",
    "sous-zone": "Plantala",
    "imgURL": "https://res.cloudinary.com/dinaj1mwf/image/upload/v1683925166/bulbuisson_aavypz.jpg"
  },
  {
    "nom": "Chafemal le Bagarreur",
    "etape": 25,
    "zone": "Amakna",
    "sous-zone": "Forêt maléfique",
    "imgURL": "https://res.cloudinary.com/dinaj1mwf/image/upload/v1683925167/chafer_ucumcp.jpg"
  },
  {
    "nom": "Chaffoin le Sournois",
    "etape": 25,
    "zone": "Plaines de Cania",
    "sous-zone": "Bois de Litneg",
    "imgURL": "https://res.cloudinary.com/dinaj1mwf/image/upload/v1683925167/chafer_fantassin_gtwozi.jpg"
  },
  {
    "nom": "Crolnareff l'Exilé",
    "etape": 25,
    "zone": "Montagnes des Koalaks",
    "sous-zone": "Marécages nauséabonds",
    "imgURL": "https://res.cloudinary.com/dinaj1mwf/image/upload/v1683925169/crocodaille_vwophn.jpg"
  },
  {
    "nom": "Cruskof le Rustre",
    "etape": 25,
    "zone": "Île d'Otomaï",
    "sous-zone": "Plage de Corail",
    "imgURL": "https://res.cloudinary.com/dinaj1mwf/image/upload/v1683925170/crustorail_morito_fnsfdx.jpg"
  },
  {
    "nom": "Crustensyl le Pragmatique",
    "etape": 25,
    "zone": "Île d'Otomaï",
    "sous-zone": "Plage de Corail",
    "imgURL": "https://res.cloudinary.com/dinaj1mwf/image/upload/v1683925170/crustorail_malibout_fvjt31.jpg"
  },
  {
    "nom": "Crustterus l'Organique",
    "etape": 25,
    "zone": "Île d'Otomaï",
    "sous-zone": "Plage de Corail",
    "imgURL": "https://res.cloudinary.com/dinaj1mwf/image/upload/v1683925170/crustorail_kouracao_iz39tg.jpg"
  },
  {
    "nom": "Dragnoute l'Irascible",
    "etape": 25,
    "zone": "Montagnes des Koalaks",
    "sous-zone": "Territoire des Dragodindes Sauvages",
    "imgURL": "https://res.cloudinary.com/dinaj1mwf/image/upload/v1683925170/dragodinde_rousse_sauvage_ltlrjv.jpg"
  },
  {
    "nom": "Farlon l'Enfant",
    "etape": 25,
    "zone": "Labyrinthe du Dragon Cochon",
    "sous-zone": "Labyrinthe du Dragon Cochon",
    "imgURL": "https://res.cloudinary.com/dinaj1mwf/image/upload/v1683925169/cochon_de_farle_qqwrjt.jpg"
  },
  {
    "nom": "Larvomatik le Propre",
    "etape": 25,
    "zone": "Amakna",
    "sous-zone": "Port de Madrestam",
    "imgURL": "https://res.cloudinary.com/dinaj1mwf/image/upload/v1683925177/larve_jaune_oi3lkc.jpg"
  },
  {
    "nom": "Radoutable le Craint",
    "etape": 25,
    "zone": "Astrub",
    "sous-zone": "Egouts d'Astrub",
    "imgURL": "https://res.cloudinary.com/dinaj1mwf/image/upload/v1683925159/rat_degoutant_malade_ykhdad.jpg"
  },
  {
    "nom": "Scaratyn l'Huître",
    "etape": 25,
    "zone": "Île du Minotoror",
    "sous-zone": "Labyrinthe du Minotoror",
    "imgURL": "https://res.cloudinary.com/dinaj1mwf/image/upload/v1683925160/scaratos_surmpd.jpg"
  },
  {
    "nom": "Scorpitène l'Enflammé",
    "etape": 25,
    "zone": "Landes de Sidimote",
    "sous-zone": "Désolation de Sidimote",
    "imgURL": "https://res.cloudinary.com/dinaj1mwf/image/upload/v1683925161/scorbute_hdn6hg.jpg"
  },
  {
    "nom": "Tronkoneuz la Tranchante",
    "etape": 25,
    "zone": "Forêt des Abraknydes",
    "sous-zone": "Orée de la forêt des Abraknydes",
    "imgURL": "https://res.cloudinary.com/dinaj1mwf/image/upload/v1683925163/tronknyde_tlhmly.jpg"
  },
  {
    "nom": "Aboudbra le Porteur",
    "etape": 26,
    "zone": "Plaines de Cania",
    "sous-zone": "Village des Dopeuls",
    "imgURL": "https://res.cloudinary.com/dinaj1mwf/image/upload/v1683925163/aboub_kofgno.jpg"
  },
  {
    "nom": "Ameur la Laide",
    "etape": 26,
    "zone": "Plaines de Cania",
    "sous-zone": "Baie de Cania",
    "imgURL": "https://res.cloudinary.com/dinaj1mwf/image/upload/v1683925164/amlub_khm9em.jpg"
  },
  {
    "nom": "Arabord la Cruche",
    "etape": 26,
    "zone": "Amakna",
    "sous-zone": "Forêt maléfique",
    "imgURL": "https://res.cloudinary.com/dinaj1mwf/image/upload/v1683925164/arakne_majeure_owiagp.jpg"
  },
  {
    "nom": "Cavordemal le Sorcier",
    "etape": 26,
    "zone": "Plaines de Cania",
    "sous-zone": "Plaines des Porkass",
    "imgURL": "https://res.cloudinary.com/dinaj1mwf/image/upload/v1683925167/cavalier_porkass_wmvziy.jpg"
  },
  {
    "nom": "Chafmarcel le Fêtard",
    "etape": 26,
    "zone": "Plaines de Cania",
    "sous-zone": "Bois de Litneg",
    "imgURL": "https://res.cloudinary.com/dinaj1mwf/image/upload/v1683925167/chafer_archer_bybm8a.jpg"
  },
  {
    "nom": "Chalan le Commerçant",
    "etape": 26,
    "zone": "Plaines de Cania",
    "sous-zone": "Bois de Litneg",
    "imgURL": "https://res.cloudinary.com/dinaj1mwf/image/upload/v1683925167/chafer_lancier_ofrebv.jpg"
  },
  {
    "nom": "Codenlgaz le Problème",
    "etape": 26,
    "zone": "Plaines de Cania",
    "sous-zone": "Baie de Cania",
    "imgURL": "https://res.cloudinary.com/dinaj1mwf/image/upload/v1683925169/codem_glihfg.jpg"
  },
  {
    "nom": "Crusmeyer le Pervers",
    "etape": 26,
    "zone": "Île d'Otomaï",
    "sous-zone": "Plage de Corail",
    "imgURL": "https://res.cloudinary.com/dinaj1mwf/image/upload/v1683925170/crustorail_passaoh_gwihz2.jpg"
  },
  {
    "nom": "Floriste la Cannibale",
    "etape": 26,
    "zone": "Île de Pandala",
    "sous-zone": "Plantala",
    "imgURL": "https://res.cloudinary.com/dinaj1mwf/image/upload/v1683925172/floristile_mhlqjl.png"
  },
  {
    "nom": "Forboyar l'Enigmatique",
    "etape": 26,
    "zone": "Amakna",
    "sous-zone": "Territoire des Bandits",
    "imgURL": "https://res.cloudinary.com/dinaj1mwf/image/upload/v1683925172/forgeron_sombre_oxmjxr.jpg"
  },
  {
    "nom": "Ginsenk le Stimulant",
    "etape": 26,
    "zone": "Plaines de Cania",
    "sous-zone": "Village des Dopeuls",
    "imgURL": "https://res.cloudinary.com/dinaj1mwf/image/upload/v1683925173/gink_bisyns.jpg"
  },
  {
    "nom": "Grandilok le Clameur",
    "etape": 26,
    "zone": "Île des Wabbits",
    "sous-zone": "Îlot de la Couronne",
    "imgURL": "https://res.cloudinary.com/dinaj1mwf/image/upload/v1683925173/grand_pa_wabbit_ppafgv.jpg"
  },
  {
    "nom": "Kiroyal le Sirupeux",
    "etape": 26,
    "zone": "Plaines de Cania",
    "sous-zone": "Baie de Cania",
    "imgURL": "https://res.cloudinary.com/dinaj1mwf/image/upload/v1683925175/kirevam_bptzbg.jpg"
  },
  {
    "nom": "Koktèle le Secoué",
    "etape": 26,
    "zone": "Île de Moon",
    "sous-zone": "Plage de la Tortue",
    "imgURL": "https://res.cloudinary.com/dinaj1mwf/image/upload/v1683925176/kokoko_xui6pe.jpg"
  },
  {
    "nom": "Let le Rond",
    "etape": 26,
    "zone": "Plaines de Cania",
    "sous-zone": "Baie de Cania",
    "imgURL": "https://res.cloudinary.com/dinaj1mwf/image/upload/v1683925177/let_emoliug_cbx4pd.jpg"
  },
  {
    "nom": "Nelvin le Boulet",
    "etape": 26,
    "zone": "Plaines de Cania",
    "sous-zone": "Village des Dopeuls",
    "imgURL": "https://res.cloudinary.com/dinaj1mwf/image/upload/v1683925179/nebgib_hmmevc.jpg"
  },
  {
    "nom": "Nipulnislip l'Exhibitionniste",
    "etape": 26,
    "zone": "Plaines de Cania",
    "sous-zone": "Village des Dopeuls",
    "imgURL": "https://res.cloudinary.com/dinaj1mwf/image/upload/v1683925157/nipul_zgd85d.jpg"
  },
  {
    "nom": "Osuxion le Vampirique",
    "etape": 26,
    "zone": "Plaines de Cania",
    "sous-zone": "Village des Dopeuls",
    "imgURL": "https://res.cloudinary.com/dinaj1mwf/image/upload/v1683925157/osurc_lmgkrj.jpg"
  },
  {
    "nom": "Susbewl l'Hypocrite",
    "etape": 26,
    "zone": "Plaines de Cania",
    "sous-zone": "Baie de Cania",
    "imgURL": "https://res.cloudinary.com/dinaj1mwf/image/upload/v1683925161/susej_bdckag.jpg"
  },
  {
    "nom": "Wokènrôl le Danseur",
    "etape": 26,
    "zone": "Île des Wabbits",
    "sous-zone": "Îlot de la Couronne",
    "imgURL": "https://res.cloudinary.com/dinaj1mwf/image/upload/v1683925163/wo_wabbit_amdtc9.jpg"
  },
  {
    "nom": "Abrakildas le Vénérable",
    "etape": 27,
    "zone": "Forêt des Abraknydes",
    "sous-zone": "Forêt Sombre",
    "imgURL": "https://res.cloudinary.com/dinaj1mwf/image/upload/v1683925164/abraknyde_venerable_z4tn2u.jpg"
  },
  {
    "nom": "Chafrit le Barbare",
    "etape": 27,
    "zone": "Brakmar",
    "sous-zone": "Cimetière des Torturés",
    "imgURL": "https://res.cloudinary.com/dinaj1mwf/image/upload/v1683925167/chafer_delite_lp50x2.jpg"
  },
  {
    "nom": "Cramikaz le Suicidaire",
    "etape": 27,
    "zone": "Plaines de Cania",
    "sous-zone": "Plaines Rocheuses",
    "imgURL": "https://res.cloudinary.com/dinaj1mwf/image/upload/v1683925169/craqueleur_des_plaines_tyz4fs.jpg"
  },
  {
    "nom": "Craquetou le Fissuré",
    "etape": 27,
    "zone": "Île d'Otomaï",
    "sous-zone": "Plaines herbeuses",
    "imgURL": "https://res.cloudinary.com/dinaj1mwf/image/upload/v1683925169/craqueboule_poli_q3prda.jpg"
  },
  {
    "nom": "Doktopuss le Maléfique",
    "etape": 27,
    "zone": "Montagnes des Koalaks",
    "sous-zone": "Lacs enchantés",
    "imgURL": "https://res.cloudinary.com/dinaj1mwf/image/upload/v1683925170/dok_alako_y0afhh.jpg"
  },
  {
    "nom": "Germinol l'Indigent",
    "etape": 27,
    "zone": "Île du Minotoror",
    "sous-zone": "Labyrinthe du Minotoror",
    "imgURL": "https://res.cloudinary.com/dinaj1mwf/image/upload/v1683925173/gamino_lbhtgp.jpg"
  },
  {
    "nom": "Grenuche la Gentille",
    "etape": 27,
    "zone": "Île de Pandala",
    "sous-zone": "Plantala",
    "imgURL": "https://res.cloudinary.com/dinaj1mwf/image/upload/v1683925173/grenufar_f73nqx.png"
  },
  {
    "nom": "Kannibal le Lecteur",
    "etape": 27,
    "zone": "Île de Moon",
    "sous-zone": "Forêt des masques",
    "imgURL": "https://res.cloudinary.com/dinaj1mwf/image/upload/v1683925174/kanniboul_archer_bq6lpr.jpg"
  },
  {
    "nom": "Kapota la Fraise",
    "etape": 27,
    "zone": "Île de Moon",
    "sous-zone": "Forêt des masques",
    "imgURL": "https://res.cloudinary.com/dinaj1mwf/image/upload/v1683925174/kanniboul_jav_vxxutt.jpg"
  },
  {
    "nom": "Koalastrof la Naturelle",
    "etape": 27,
    "zone": "Montagnes des Koalaks",
    "sous-zone": "Lacs enchantés",
    "imgURL": "https://res.cloudinary.com/dinaj1mwf/image/upload/v1683925175/koalak_immature_ebg3xh.jpg"
  },
  {
    "nom": "Koko la Violente",
    "etape": 27,
    "zone": "Île de Pandala",
    "sous-zone": "Akwadala",
    "imgURL": "https://res.cloudinary.com/dinaj1mwf/image/upload/v1683925176/kokom_ho4dmh.png"
  },
  {
    "nom": "Maître Onom le Régulier",
    "etape": 27,
    "zone": "Plaines de Cania",
    "sous-zone": "Routes Rocailleuses",
    "imgURL": "https://res.cloudinary.com/dinaj1mwf/image/upload/v1683925178/maitre_bolet_t24zzu.jpg"
  },
  {
    "nom": "Ouashouash l'Exubérant",
    "etape": 27,
    "zone": "Île d'Otomaï",
    "sous-zone": "Tourbière sans fond",
    "imgURL": "https://res.cloudinary.com/dinaj1mwf/image/upload/v1683925177/le_ouassingue_entourbe_scdaoi.jpg"
  },
  {
    "nom": "Ouassébo l'Esthète",
    "etape": 27,
    "zone": "Astrub",
    "sous-zone": "Cimetière d'Astrub",
    "imgURL": "https://res.cloudinary.com/dinaj1mwf/image/upload/v1683925177/le_ouassingue_vmdatj.jpg"
  },
  {
    "nom": "Ouature la Mobile",
    "etape": 27,
    "zone": "Astrub",
    "sous-zone": "Cimetière d'Astrub",
    "imgURL": "https://res.cloudinary.com/dinaj1mwf/image/upload/v1683925177/la_ouassingue_gavnz5.jpg"
  },
  {
    "nom": "Palmiche le Serein",
    "etape": 27,
    "zone": "Île d'Otomaï",
    "sous-zone": "Plage de Corail",
    "imgURL": "https://res.cloudinary.com/dinaj1mwf/image/upload/v1683925157/palmifleur_morito_vy0l4t.jpg"
  },
  {
    "nom": "Palmiflette le Convivial",
    "etape": 27,
    "zone": "Île d'Otomaï",
    "sous-zone": "Plage de Corail",
    "imgURL": "https://res.cloudinary.com/dinaj1mwf/image/upload/v1683925157/palmifleur_passaoh_hpx29l.jpg"
  },
  {
    "nom": "Palmito le Menteur",
    "etape": 27,
    "zone": "Île d'Otomaï",
    "sous-zone": "Plage de Corail",
    "imgURL": "https://res.cloudinary.com/dinaj1mwf/image/upload/v1683925157/palmifleur_malibout_ihrgzu.jpg"
  },
  {
    "nom": "Ramitant le Dilettante",
    "etape": 27,
    "zone": "Amakna",
    "sous-zone": "Souterrains du Château d'Amakna",
    "imgURL": "https://res.cloudinary.com/dinaj1mwf/image/upload/v1683925157/palmifleur_malibout_ihrgzu.jpg"
  },
  {
    "nom": "Sampi l'Eternel",
    "etape": 27,
    "zone": "Plaines de Cania",
    "sous-zone": "Plaines des Porkass",
    "imgURL": "https://res.cloudinary.com/dinaj1mwf/image/upload/v1683925160/sanglier_des_plaines_x09abs.jpg"
  },
  {
    "nom": "Akaka le Souillé",
    "etape": 28,
    "zone": "Île de Pandala",
    "sous-zone": "Akwadala",
    "imgURL": "https://res.cloudinary.com/dinaj1mwf/image/upload/v1683925164/akakwa_ejc7hx.png"
  },
  {
    "nom": "Bebetto l'Intellectuel",
    "etape": 28,
    "zone": "Île de Pandala",
    "sous-zone": "Akwadala",
    "imgURL": "https://res.cloudinary.com/dinaj1mwf/image/upload/v1683925165/betto_e49yfc.png"
  },
  {
    "nom": "Corboyard l'Enigmatique",
    "etape": 28,
    "zone": "Île d'Otomaï",
    "sous-zone": "Plage de Corail",
    "imgURL": "https://res.cloudinary.com/dinaj1mwf/image/upload/v1683925169/corailleur_qv02sv.jpg"
  },
  {
    "nom": "Dragioli le Succulent",
    "etape": 28,
    "zone": "Amakna",
    "sous-zone": "Sanctuaires des Dragoeufs",
    "imgURL": "https://res.cloudinary.com/dinaj1mwf/image/upload/v1683925170/dragace_gb5muz.png"
  },
  {
    "nom": "Kannémik le Maigre",
    "etape": 28,
    "zone": "Île de Moon",
    "sous-zone": "Forêt des masques",
    "imgURL": "https://res.cloudinary.com/dinaj1mwf/image/upload/v1683925174/kanniboul_sarbak_exnfam.jpg"
  },
  {
    "nom": "Kannisterik le Forcené",
    "etape": 28,
    "zone": "Île de Moon",
    "sous-zone": "Forêt des masques",
    "imgURL": "https://res.cloudinary.com/dinaj1mwf/image/upload/v1683925174/kanniboul_thierry_y3gaqp.jpg"
  },
  {
    "nom": "Kwakamole l'Appétissant",
    "etape": 28,
    "zone": "Amakna",
    "sous-zone": "Montagne des Craqueleurs",
    "imgURL": "https://res.cloudinary.com/dinaj1mwf/image/upload/v1683925177/kwak_de_terre_csxfvs.png"
  },
  {
    "nom": "Kwaké le Piraté",
    "etape": 28,
    "zone": "Amakna",
    "sous-zone": "Montagne des Craqueleurs",
    "imgURL": "https://res.cloudinary.com/dinaj1mwf/image/upload/v1683925177/kwak_de_vent_ofuwpd.png"
  },
  {
    "nom": "Kwakolak le Chocolaté",
    "etape": 28,
    "zone": "Amakna",
    "sous-zone": "Montagne des Craqueleurs",
    "imgURL": "https://res.cloudinary.com/dinaj1mwf/image/upload/v1683925177/kwak_de_flamme_ox2pfl.png"
  },
  {
    "nom": "Kwakwatique le Trempé",
    "etape": 28,
    "zone": "Amakna",
    "sous-zone": "Montagne des Craqueleurs",
    "imgURL": "https://res.cloudinary.com/dinaj1mwf/image/upload/v1683925176/kwak_de_glace_x5noi8.png"
  },
  {
    "nom": "Moumoute la Douce",
    "etape": 28,
    "zone": "Baie de Sufokia",
    "sous-zone": "Rivage sufokien",
    "imgURL": "https://res.cloudinary.com/dinaj1mwf/image/upload/v1683925180/moumoule_tahcf1.png"
  },
  {
    "nom": "Ougaould le Parasite",
    "etape": 28,
    "zone": "Brakmar",
    "sous-zone": "Cimetière des Torturés",
    "imgURL": "https://res.cloudinary.com/dinaj1mwf/image/upload/v1683925167/chafer_draugr_gerv7u.jpg"
  },
  {
    "nom": "Palmbytch la Bronzée",
    "etape": 28,
    "zone": "Île d'Otomaï",
    "sous-zone": "Plage de Corail",
    "imgURL": "https://res.cloudinary.com/dinaj1mwf/image/upload/v1683925157/palmifleur_kouracao_chy1jg.jpg"
  },
  {
    "nom": "Parapadkouï l'Émasculé",
    "etape": 28,
    "zone": "Île de Pandala",
    "sous-zone": "Terrdala",
    "imgURL": "https://res.cloudinary.com/dinaj1mwf/image/upload/v1683925158/parashukoui_tvicu3.png"
  },
  {
    "nom": "Porsalé le Râleur",
    "etape": 28,
    "zone": "Labyrinthe du Dragon Cochon",
    "sous-zone": "Labyrinthe du Dragon Cochon",
    "imgURL": "https://res.cloudinary.com/dinaj1mwf/image/upload/v1683925159/porsalu_hdfyo3.png"
  },
  {
    "nom": "Ratlbol l'Aigri",
    "etape": 28,
    "zone": "Amakna",
    "sous-zone": "Souterrains du Château d'Amakna",
    "imgURL": "https://res.cloudinary.com/dinaj1mwf/image/upload/v1683925159/rat_degoutant_q2b2um.jpg"
  },
  {
    "nom": "Rauligo le Sale",
    "etape": 28,
    "zone": "Baie de Sufokia",
    "sous-zone": "Rivage sufokien",
    "imgURL": "https://res.cloudinary.com/dinaj1mwf/image/upload/v1683925159/raul_mops_wcuv2d.jpg"
  },
  {
    "nom": "Sarkastik l'Incompris",
    "etape": 28,
    "zone": "Île de Pandala",
    "sous-zone": "Akwadala",
    "imgURL": "https://res.cloudinary.com/dinaj1mwf/image/upload/v1683925160/sarkapwane_f8twqk.png"
  },
  {
    "nom": "Serpistule le Purulent",
    "etape": 28,
    "zone": "Île du Minotoror",
    "sous-zone": "Labyrinthe du Minotoror",
    "imgURL": "https://res.cloudinary.com/dinaj1mwf/image/upload/v1683925161/serpiplume_z299t9.jpg"
  },
  {
    "nom": "Vétaurine L'énergisé",
    "etape": 28,
    "zone": "Plaines de Cania",
    "sous-zone": "Routes Rocailleuses",
    "imgURL": "https://res.cloudinary.com/dinaj1mwf/image/upload/v1683925162/vetauran_qisk3o.png"
  },
  {
    "nom": "Barebourd le Comte",
    "etape": 29,
    "zone": "Île d'Otomaï",
    "sous-zone": "Arche d'Otomaï",
    "imgURL": "https://res.cloudinary.com/dinaj1mwf/image/upload/v1683925164/barbroussa_zdxvdt.jpg"
  },
  {
    "nom": "Caboume l'Artilleur",
    "etape": 29,
    "zone": "Île d'Otomaï",
    "sous-zone": "Chemin du Crâne",
    "imgURL": "https://res.cloudinary.com/dinaj1mwf/image/upload/v1683925166/canon_dorf_u1ghha.jpg"
  },
  {
    "nom": "Chiendanlémin l'Illusionniste",
    "etape": 29,
    "zone": "Île d'Otomaï",
    "sous-zone": "Jungle Obscure",
    "imgURL": "https://res.cloudinary.com/dinaj1mwf/image/upload/v1683925168/chiendent_anr0sa.jpg"
  },
  {
    "nom": "Dragkouine la Déguisée",
    "etape": 29,
    "zone": "Amakna",
    "sous-zone": "Presqu'île des Dragoeufs",
    "imgURL": "https://res.cloudinary.com/dinaj1mwf/image/upload/v1683925171/dragoeuf_dore_zpzga9.jpg"
  },
  {
    "nom": "Dragmoclaiss le Fataliste",
    "etape": 29,
    "zone": "Amakna",
    "sous-zone": "Presqu'île des Dragoeufs",
    "imgURL": "https://res.cloudinary.com/dinaj1mwf/image/upload/v1683925171/dragoeuf_de_saphir_qaj8zk.jpg"
  },
  {
    "nom": "Dragnostik le Sceptique",
    "etape": 29,
    "zone": "Amakna",
    "sous-zone": "Presqu'île des Dragoeufs",
    "imgURL": "https://res.cloudinary.com/dinaj1mwf/image/upload/v1683925171/dragoeuf_de_saphir_qaj8zk.jpg"
  },
  {
    "nom": "Dragstayr le Fonceur",
    "etape": 29,
    "zone": "Amakna",
    "sous-zone": "Presqu'île des Dragoeufs",
    "imgURL": "https://res.cloudinary.com/dinaj1mwf/image/upload/v1683925171/dragoeuf_blanc_vxrysh.jpg"
  },
  {
    "nom": "Fandanleuil le Précis",
    "etape": 29,
    "zone": "Brakmar",
    "sous-zone": "Bordure de Brakmar",
    "imgURL": "https://res.cloudinary.com/dinaj1mwf/image/upload/v1683925172/fantome_ardent_cwvvn9.jpg"
  },
  {
    "nom": "Fanlabiz le Véloce",
    "etape": 29,
    "zone": "Brakmar",
    "sous-zone": "Bordure de Brakmar",
    "imgURL": "https://res.cloudinary.com/dinaj1mwf/image/upload/v1683925172/fantome_apero_rg9uwx.jpg"
  },
  {
    "nom": "Fantoch le Pantin",
    "etape": 29,
    "zone": "Brakmar",
    "sous-zone": "Bordure de Brakmar",
    "imgURL": "https://res.cloudinary.com/dinaj1mwf/image/upload/v1683925172/fantome_arepo_fjlibc.png"
  },
  {
    "nom": "Fantrask la Rêveuse",
    "etape": 29,
    "zone": "Brakmar",
    "sous-zone": "Bordure de Brakmar",
    "imgURL": "https://res.cloudinary.com/dinaj1mwf/image/upload/v1683925172/fantome_brave_qdjprx.jpg"
  },
  {
    "nom": "Koakofrui le Confit",
    "etape": 29,
    "zone": "Montagnes des Koalaks",
    "sous-zone": "Canyon sauvage",
    "imgURL": "https://res.cloudinary.com/dinaj1mwf/image/upload/v1683925175/koalak_griotte_f9d6d2.jpg"
  },
  {
    "nom": "Koamaembair le Coulant",
    "etape": 29,
    "zone": "Montagnes des Koalaks",
    "sous-zone": "Canyon sauvage",
    "imgURL": "https://res.cloudinary.com/dinaj1mwf/image/upload/v1683925175/koalak_coco_xhkh7d.jpg"
  },
  {
    "nom": "Koarmit la Batracienne",
    "etape": 29,
    "zone": "Montagnes des Koalaks",
    "sous-zone": "Canyon sauvage",
    "imgURL": "https://res.cloudinary.com/dinaj1mwf/image/upload/v1683925176/koalak_reinette_wrpogx.jpg"
  },
  {
    "nom": "Koaskette la Chapelière",
    "etape": 29,
    "zone": "Montagnes des Koalaks",
    "sous-zone": "Canyon sauvage",
    "imgURL": "https://res.cloudinary.com/dinaj1mwf/image/upload/v1683925176/koalak_indigo_na78kh.jpg"
  },
  {
    "nom": "Nakuneuye le Borgne",
    "etape": 29,
    "zone": "Île d'Otomaï",
    "sous-zone": "Chemin du Crâne",
    "imgURL": "https://res.cloudinary.com/dinaj1mwf/image/upload/v1683925179/nakunbra_y4xfsp.jpg"
  },
  {
    "nom": "Nerdeubeu le Flagellant",
    "etape": 29,
    "zone": "Île d'Otomaï",
    "sous-zone": "Jungle Obscure",
    "imgURL": "https://res.cloudinary.com/dinaj1mwf/image/upload/v1683925156/nerbe_jdhvtl.jpg"
  },
  {
    "nom": "Ratéhaifaim le Professeur",
    "etape": 29,
    "zone": "Amakna",
    "sous-zone": "Souterrains du Château d'Amakna",
    "imgURL": "https://res.cloudinary.com/dinaj1mwf/image/upload/v1683925159/rat_dhyoactif_pcocef.jpg"
  },
  {
    "nom": "Sparoket le Lanceur",
    "etape": 29,
    "zone": "Île d'Otomaï",
    "sous-zone": "Arche d'Otomaï",
    "imgURL": "https://res.cloudinary.com/dinaj1mwf/image/upload/v1683925161/sparo_jxevol.jpg"
  },
  {
    "nom": "Tilolo la Bien Moulée",
    "etape": 29,
    "zone": "Île de Pandala",
    "sous-zone": "Terrdala",
    "imgURL": "https://res.cloudinary.com/dinaj1mwf/image/upload/v1683925178/lolojiki_gtyymn.png"
  },
  {
    "nom": "Alhoui le Répondeur",
    "etape": 30,
    "zone": "Plaines de Cania",
    "sous-zone": "Dents de Pierre",
    "imgURL": "https://res.cloudinary.com/dinaj1mwf/image/upload/v1683925164/alhyene_ed5um0.png"
  },
  {
    "nom": "Bonpake le Chavireur",
    "etape": 30,
    "zone": "Île de Pandala",
    "sous-zone": "Terrdala",
    "imgURL": "https://res.cloudinary.com/dinaj1mwf/image/upload/v1683925174/ishigro-pake_jiy0gx.png"
  },
  {
    "nom": "Bourde le Maladroit",
    "etape": 30,
    "zone": "Plaines de Cania",
    "sous-zone": "Champs de Cania",
    "imgURL": "https://res.cloudinary.com/dinaj1mwf/image/upload/v1683925166/bourdard_rotlgh.png"
  },
  {
    "nom": "Crathdogue le Cruel",
    "etape": 30,
    "zone": "Île d'Otomaï",
    "sous-zone": "Plaines herbeuses",
    "imgURL": "https://res.cloudinary.com/dinaj1mwf/image/upload/v1683925169/craqueleur_poli_dv2hbz.jpg"
  },
  {
    "nom": "Crok le Beau",
    "etape": 30,
    "zone": "Montagnes des Koalaks",
    "sous-zone": "Marécages nauséabonds",
    "imgURL": "https://res.cloudinary.com/dinaj1mwf/image/upload/v1683925168/chef_crocodaille_ugieyt.jpg"
  },
  {
    "nom": "Dragonienne l'Econome",
    "etape": 30,
    "zone": "Amakna",
    "sous-zone": "Sanctuaires des Dragoeufs",
    "imgURL": "https://res.cloudinary.com/dinaj1mwf/image/upload/v1683925171/dragueuse_wnuvcm.jpg"
  },
  {
    "nom": "Félyssion la Gourmande",
    "etape": 30,
    "zone": "Plaines de Cania",
    "sous-zone": "Dents de Pierre",
    "imgURL": "https://res.cloudinary.com/dinaj1mwf/image/upload/v1683925172/felygiene_itmzww.png"
  },
  {
    "nom": "Fouflay le Retombé",
    "etape": 30,
    "zone": "Plaines de Cania",
    "sous-zone": "Routes Rocailleuses",
    "imgURL": "https://res.cloudinary.com/dinaj1mwf/image/upload/v1683925173/foufayteur_zuytyh.png"
  },
  {
    "nom": "Guerrite le Veilleur",
    "etape": 30,
    "zone": "Montagnes des Koalaks",
    "sous-zone": "Vallée de la Morh'Kitu",
    "imgURL": "https://res.cloudinary.com/dinaj1mwf/image/upload/v1683925174/guerrier_koalak_uh6q8q.jpg"
  },
  {
    "nom": "Kanasukr le Mielleux",
    "etape": 30,
    "zone": "Plaines de Cania",
    "sous-zone": "Routes Rocailleuses",
    "imgURL": "https://res.cloudinary.com/dinaj1mwf/image/upload/v1683925174/kanigrou_vlfg6q.jpg"
  },
  {
    "nom": "Kanibière l'Encordée",
    "etape": 30,
    "zone": "Plaines de Cania",
    "sous-zone": "Dents de Pierre",
    "imgURL": "https://res.cloudinary.com/dinaj1mwf/image/upload/v1683925175/kaniblou_qqn2vh.png"
  },
  {
    "nom": "Kido l'Âtre",
    "etape": 30,
    "zone": "Île d'Otomaï",
    "sous-zone": "Plaines herbeuses",
    "imgURL": "https://res.cloudinary.com/dinaj1mwf/image/upload/v1683925175/kido_khjz2a.jpg"
  },
  {
    "nom": "Kilimanj'haro le Grimpeur",
    "etape": 30,
    "zone": "Île d'Otomaï",
    "sous-zone": "Plaines herbeuses",
    "imgURL": "https://res.cloudinary.com/dinaj1mwf/image/upload/v1683925175/kilibriss_e6tnxg.jpg"
  },
  {
    "nom": "Larvaloeil l'Émue",
    "etape": 30,
    "zone": "Plaines de Cania",
    "sous-zone": "Champs de Cania",
    "imgURL": "https://res.cloudinary.com/dinaj1mwf/image/upload/v1683925177/larve_champetre_wq3sil.png"
  },
  {
    "nom": "Mufguedin le Suprême",
    "etape": 30,
    "zone": "Île d'Otomaï",
    "sous-zone": "Plaines herbeuses",
    "imgURL": "https://res.cloudinary.com/dinaj1mwf/image/upload/v1683925179/mufafah_conl4c.jpg"
  },
  {
    "nom": "Muloufok l'Hilarant",
    "etape": 30,
    "zone": "Landes de Sidimote",
    "sous-zone": "Hauts des Hurlements",
    "imgURL": "https://res.cloudinary.com/dinaj1mwf/image/upload/v1683925179/mulou_jnhtay.jpg"
  },
  {
    "nom": "Orfélyre le Charmeur",
    "etape": 30,
    "zone": "Plaines de Cania",
    "sous-zone": "Dents de Pierre",
    "imgURL": "https://res.cloudinary.com/dinaj1mwf/image/upload/v1683925157/orfelin_ueesq8.png"
  },
  {
    "nom": "Pantacour le Long",
    "etape": 30,
    "zone": "Plaines de Cania",
    "sous-zone": "Dents de Pierre",
    "imgURL": "https://res.cloudinary.com/dinaj1mwf/image/upload/v1683925158/panthegros_bqlbrv.png"
  },
  {
    "nom": "Souristiti l'Immortalisée",
    "etape": 30,
    "zone": "Plaines de Cania",
    "sous-zone": "Champs de Cania",
    "imgURL": "https://res.cloudinary.com/dinaj1mwf/image/upload/v1683925161/souris_verte_prqe9d.png"
  },
  {
    "nom": "Toufou le Benêt",
    "etape": 30,
    "zone": "Île d'Otomaï",
    "sous-zone": "Plaines herbeuses",
    "imgURL": "https://res.cloudinary.com/dinaj1mwf/image/upload/v1683925165/bitouf_des_plaines_sjeljq.jpg"
  },
  {
    "nom": "Abrakanette l'Encapsulé",
    "etape": 31,
    "zone": "Forêt des Abraknydes",
    "sous-zone": "Forêt Sombre",
    "imgURL": "https://res.cloudinary.com/dinaj1mwf/image/upload/v1683925164/abraknyde_sombre_j7hub4.jpg"
  },
  {
    "nom": "Abraklette le Fondant",
    "etape": 31,
    "zone": "Forêt des Abraknydes",
    "sous-zone": "Forêt Sombre",
    "imgURL": "https://res.cloudinary.com/dinaj1mwf/image/upload/v1683925164/abrakne_sombre_lf1usl.jpg"
  },
  {
    "nom": "Bitoven le Musicien",
    "etape": 31,
    "zone": "Île d'Otomaï",
    "sous-zone": "Jungle Obscure",
    "imgURL": "https://res.cloudinary.com/dinaj1mwf/image/upload/v1683925165/bitouf_sombre_dhmej9.jpg"
  },
  {
    "nom": "Brouste l'Humiliant",
    "etape": 31,
    "zone": "Île d'Otomaï",
    "sous-zone": "Jungle Obscure",
    "imgURL": "https://res.cloudinary.com/dinaj1mwf/image/upload/v1683925166/brouture_oenegq.jpg"
  },
  {
    "nom": "Craquecrac l'Endurant",
    "etape": 31,
    "zone": "Plaines de Cania",
    "sous-zone": "Plaines Rocheuses",
    "imgURL": "https://res.cloudinary.com/dinaj1mwf/image/upload/v1683925169/craquelourd_hofjvx.png"
  },
  {
    "nom": "Diskord le Belliqueux",
    "etape": 31,
    "zone": "Île d'Otomaï",
    "sous-zone": "Village de la Canopée",
    "imgURL": "https://res.cloudinary.com/dinaj1mwf/image/upload/v1683925170/disciple_zoth_jo3gvz.jpg"
  },
  {
    "nom": "Dragdikal le Décisif",
    "etape": 31,
    "zone": "Amakna",
    "sous-zone": "Sanctuaires des Dragoeufs",
    "imgURL": "https://res.cloudinary.com/dinaj1mwf/image/upload/v1683925171/dragoeuf_guerrier_wh0mpt.jpg"
  },
  {
    "nom": "Dragobert le Monarque",
    "etape": 31,
    "zone": "Amakna",
    "sous-zone": "Sanctuaires des Dragoeufs",
    "imgURL": "https://res.cloudinary.com/dinaj1mwf/image/upload/v1683925171/dragoeuf_volant_nojuje.jpg"
  },
  {
    "nom": "Fossamoel le Juteux",
    "etape": 31,
    "zone": "Montagnes des Koalaks",
    "sous-zone": "Cimetière primitif",
    "imgURL": "https://res.cloudinary.com/dinaj1mwf/image/upload/v1683925172/fossoyeur_koalak_sngswp.jpg"
  },
  {
    "nom": "Gloubibou le Gars",
    "etape": 31,
    "zone": "Île de Moon",
    "sous-zone": "Jungle interdite",
    "imgURL": "https://res.cloudinary.com/dinaj1mwf/image/upload/v1683925173/gloutovore_tzzkoo.jpg"
  },
  {
    "nom": "Inopenope le Négatif",
    "etape": 31,
    "zone": "Île de Pandala",
    "sous-zone": "Aerdala",
    "imgURL": "https://res.cloudinary.com/dinaj1mwf/image/upload/v1683925174/ino-naru_xeaqdv.png"
  },
  {
    "nom": "Koamag'oel le Défiguré",
    "etape": 31,
    "zone": "Montagnes des Koalaks",
    "sous-zone": "Cimetière primitif",
    "imgURL": "https://res.cloudinary.com/dinaj1mwf/image/upload/v1683925168/chevaucheur_koalak_ipgt4y.jpg"
  },
  {
    "nom": "Koasossyal le Psychopathe",
    "etape": 31,
    "zone": "Montagnes des Koalaks",
    "sous-zone": "Forêt de Kaliptus",
    "imgURL": "https://res.cloudinary.com/dinaj1mwf/image/upload/v1683925175/koalak_forestier_pxye4r.jpg"
  },
  {
    "nom": "Lichangora l'Immaculée",
    "etape": 31,
    "zone": "Île de Pandala",
    "sous-zone": "Aerdala",
    "imgURL": "https://res.cloudinary.com/dinaj1mwf/image/upload/v1683925178/lichangoro_ywth5a.png"
  },
  {
    "nom": "Meuroup le Prêtre",
    "etape": 31,
    "zone": "Île d'Otomaï",
    "sous-zone": "Tronc de l'Arbre Hakam",
    "imgURL": "https://res.cloudinary.com/dinaj1mwf/image/upload/v1683925179/meupette_xzxzxd.jpg"
  },
  {
    "nom": "Pékeutar le Tireur",
    "etape": 31,
    "zone": "Montagnes des Koalaks",
    "sous-zone": "Lacs enchantés",
    "imgURL": "https://res.cloudinary.com/dinaj1mwf/image/upload/v1683925158/pekeualak_ooxhkf.jpg"
  },
  {
    "nom": "Piradain le Pingre",
    "etape": 31,
    "zone": "Montagnes des Koalaks",
    "sous-zone": "Lacs enchantés",
    "imgURL": "https://res.cloudinary.com/dinaj1mwf/image/upload/v1683925159/piralak_pzedt0.jpg"
  },
  {
    "nom": "Rooroku l'Imposant",
    "etape": 31,
    "zone": "Île de Pandala",
    "sous-zone": "Aerdala",
    "imgURL": "https://res.cloudinary.com/dinaj1mwf/image/upload/v1683925176/kurookin_lnlzkt.png"
  },
  {
    "nom": "Tétonée la Plantureuse",
    "etape": 31,
    "zone": "Île de Pandala",
    "sous-zone": "Terrdala",
    "imgURL": "https://res.cloudinary.com/dinaj1mwf/image/upload/v1683925161/tetonuki_dbumk6.png"
  },
  {
    "nom": "Warkolad l'Etreinte",
    "etape": 31,
    "zone": "Montagnes des Koalaks",
    "sous-zone": "Canyon sauvage",
    "imgURL": "https://res.cloudinary.com/dinaj1mwf/image/upload/v1683925163/warko_marron_atbcvs.jpg"
  },
  {
    "nom": "Abrakine le Sombre",
    "etape": 32,
    "zone": "Île d'Otomaï",
    "sous-zone": "Jungle Obscure",
    "imgURL": "https://res.cloudinary.com/dinaj1mwf/image/upload/v1683925163/abrakleur_sombre_aupcjr.jpg"
  },
  {
    "nom": "Bouliver le Géant",
    "etape": 32,
    "zone": "Île d'Otomaï",
    "sous-zone": "Tourbière sans fond",
    "imgURL": "https://res.cloudinary.com/dinaj1mwf/image/upload/v1683925166/bourbassingue_rfbfen.jpg"
  },
  {
    "nom": "Drageaufol la Joyeuse",
    "etape": 32,
    "zone": "Amakna",
    "sous-zone": "Village des Dragoeufs",
    "imgURL": "https://res.cloudinary.com/dinaj1mwf/image/upload/v1683925171/dragoss_de_saphir_eveille_lj9nyg.jpg"
  },
  {
    "nom": "Dragminster le Magicien",
    "etape": 32,
    "zone": "Amakna",
    "sous-zone": "Village des Dragoeufs",
    "imgURL": "https://res.cloudinary.com/dinaj1mwf/image/upload/v1683925171/dragoss_blanc_eveille_s7ot2x.jpg"
  },
  {
    "nom": "Dragtarus le Bellâtre",
    "etape": 32,
    "zone": "Amakna",
    "sous-zone": "Village des Dragoeufs",
    "imgURL": "https://res.cloudinary.com/dinaj1mwf/image/upload/v1683925171/dragoss_dore_eveille_cz9wmf.jpg"
  },
  {
    "nom": "Drakolage le Tentateur",
    "etape": 32,
    "zone": "Montagnes des Koalaks",
    "sous-zone": "Canyon sauvage",
    "imgURL": "https://res.cloudinary.com/dinaj1mwf/image/upload/v1683925171/drakoalak_fl1ktj.jpg"
  },
  {
    "nom": "Draquetteur le Voleur",
    "etape": 32,
    "zone": "Amakna",
    "sous-zone": "Village des Dragoeufs",
    "imgURL": "https://res.cloudinary.com/dinaj1mwf/image/upload/v1683925171/dragoss_noir_eveille_y3cg2l.jpg"
  },
  {
    "nom": "Ecorfé la Vive",
    "etape": 32,
    "zone": "Île d'Otomaï",
    "sous-zone": "Jungle Obscure",
    "imgURL": "https://res.cloudinary.com/dinaj1mwf/image/upload/v1683925172/fecorce_i3xza5.jpg"
  },
  {
    "nom": "Fangshui la Dysorthographiée",
    "etape": 32,
    "zone": "Île de Pandala",
    "sous-zone": "Aerdala",
    "imgURL": "https://res.cloudinary.com/dinaj1mwf/image/upload/v1683925172/fangshu_s8ph6r.png"
  },
  {
    "nom": "Faufoll la Joyeuse",
    "etape": 32,
    "zone": "Montagnes des Koalaks",
    "sous-zone": "Vallée de la Morh'Kitu",
    "imgURL": "https://res.cloudinary.com/dinaj1mwf/image/upload/v1683925172/fauchalak_mn9f0n.jpg"
  },
  {
    "nom": "Floanna la Blonde",
    "etape": 32,
    "zone": "Île d'Otomaï",
    "sous-zone": "Jungle Obscure",
    "imgURL": "https://res.cloudinary.com/dinaj1mwf/image/upload/v1683925172/floribonde_wmjqcf.jpg"
  },
  {
    "nom": "Gastroth la Contagieuse",
    "etape": 32,
    "zone": "Île d'Otomaï",
    "sous-zone": "Village de la Canopée",
    "imgURL": "https://res.cloudinary.com/dinaj1mwf/image/upload/v1683925173/gamine_zoth_uoiml8.jpg"
  },
  {
    "nom": "Guerumoth le Collant",
    "etape": 32,
    "zone": "Île d'Otomaï",
    "sous-zone": "Village de la Canopée",
    "imgURL": "https://res.cloudinary.com/dinaj1mwf/image/upload/v1683925174/guerrier_zoth_wdrcog.jpg"
  },
  {
    "nom": "Koalaboi le Calorifère",
    "etape": 32,
    "zone": "Montagnes des Koalaks",
    "sous-zone": "Vallée de la Morh'Kitu",
    "imgURL": "https://res.cloudinary.com/dinaj1mwf/image/upload/v1683925175/koalak_farouche_rzb6tb.jpg"
  },
  {
    "nom": "Koalvissie le Chauve",
    "etape": 32,
    "zone": "Montagnes des Koalaks",
    "sous-zone": "Vallée de la Morh'Kitu",
    "imgURL": "https://res.cloudinary.com/dinaj1mwf/image/upload/v1683925176/koalak_sanguin_qsq337.jpg"
  },
  {
    "nom": "Mamakomou l'Âge",
    "etape": 32,
    "zone": "Montagnes des Koalaks",
    "sous-zone": "Canyon sauvage",
    "imgURL": "https://res.cloudinary.com/dinaj1mwf/image/upload/v1683925178/mama_koalak_vzlp5y.jpg"
  },
  {
    "nom": "Momikonos la Bandelette",
    "etape": 32,
    "zone": "Montagnes des Koalaks",
    "sous-zone": "Cimetière primitif",
    "imgURL": "https://res.cloudinary.com/dinaj1mwf/image/upload/v1683925179/momie_koalak_zpfivq.jpg"
  },
  {
    "nom": "Pétarfoutu le Mouillé",
    "etape": 32,
    "zone": "Île de Pandala",
    "sous-zone": "Feudala",
    "imgURL": "https://res.cloudinary.com/dinaj1mwf/image/upload/v1683925159/petartifoux_dwaly1.png"
  },
  {
    "nom": "Tourbiket le Virevoletant",
    "etape": 32,
    "zone": "Île d'Otomaï",
    "sous-zone": "Tourbière sans fond",
    "imgURL": "https://res.cloudinary.com/dinaj1mwf/image/upload/v1683925162/tourbassingue_aavfxs.jpg"
  },
  {
    "nom": "Wara l'Amer",
    "etape": 32,
    "zone": "Montagnes des Koalaks",
    "sous-zone": "Vallée de la Morh'Kitu",
    "imgURL": "https://res.cloudinary.com/dinaj1mwf/image/upload/v1683925163/warko_violet_t1c2qi.jpg"
  },
  {
    "nom": "Abrinos le Clair",
    "etape": 33,
    "zone": "Île d'Otomaï",
    "sous-zone": "Tronc de l'Arbre Hakam",
    "imgURL": "https://res.cloudinary.com/dinaj1mwf/image/upload/v1683925163/abrakleur_clair_pqe0sa.jpg"
  },
  {
    "nom": "Bigbadaboum l'Élémentaire",
    "etape": 33,
    "zone": "Île de Pandala",
    "sous-zone": "Feudala",
    "imgURL": "https://res.cloudinary.com/dinaj1mwf/image/upload/v1683925165/boumbardier_egd4ry.png"
  },
  {
    "nom": "Chamiléro le Malchanceux",
    "etape": 33,
    "zone": "Landes de Sidimote",
    "sous-zone": "Domaine des Fungus",
    "imgURL": "https://res.cloudinary.com/dinaj1mwf/image/upload/v1683925168/champaknyde_vmigtp.jpg"
  },
  {
    "nom": "Chamoute le Duveteux",
    "etape": 33,
    "zone": "Landes de Sidimote",
    "sous-zone": "Caverne des Fungus",
    "imgURL": "https://res.cloudinary.com/dinaj1mwf/image/upload/v1683925168/champodonte_prs2pl.jpg"
  },
  {
    "nom": "Champmé le Méchant",
    "etape": 33,
    "zone": "Landes de Sidimote",
    "sous-zone": "Caverne des Fungus",
    "imgURL": "https://res.cloudinary.com/dinaj1mwf/image/upload/v1683925168/champmane_r2cw3y.jpg"
  },
  {
    "nom": "Champolyon le Polyglotte",
    "etape": 33,
    "zone": "Landes de Sidimote",
    "sous-zone": "Caverne des Fungus",
    "imgURL": "https://res.cloudinary.com/dinaj1mwf/image/upload/v1683925167/champ_a_gnons_tn8gcv.jpg"
  },
  {
    "nom": "Champoul l'Illuminé",
    "etape": 33,
    "zone": "Landes de Sidimote",
    "sous-zone": "Caverne des Fungus",
    "imgURL": "https://res.cloudinary.com/dinaj1mwf/image/upload/v1683925168/champbis_czw3wr.jpg"
  },
  {
    "nom": "Crachefouxtre le Surpris",
    "etape": 33,
    "zone": "Île de Pandala",
    "sous-zone": "Feudala",
    "imgURL": "https://res.cloudinary.com/dinaj1mwf/image/upload/v1683925169/crachefoux_bsjwxl.png"
  },
  {
    "nom": "Don Kizoth l'Obstiné",
    "etape": 33,
    "zone": "Île d'Otomaï",
    "sous-zone": "Village de la Canopée",
    "imgURL": "https://res.cloudinary.com/dinaj1mwf/image/upload/v1683925178/maitre_zoth_qnqmwz.jpg"
  },
  {
    "nom": "Jiankor le Radoteur",
    "etape": 33,
    "zone": "Île de Grobe",
    "sous-zone": "Cimetière de Grobe",
    "imgURL": "https://res.cloudinary.com/dinaj1mwf/image/upload/v1683925174/jiangshi-nobi_zemurv.png"
  },
  {
    "nom": "Kaskapointhe la Couverte",
    "etape": 33,
    "zone": "Île d'Otomaï",
    "sous-zone": "Tronc de l'Arbre Hakam",
    "imgURL": "https://res.cloudinary.com/dinaj1mwf/image/upload/v1683925175/kaskargo_v31fcl.jpg"
  },
  {
    "nom": "Maître Koantik le Théoricien",
    "etape": 33,
    "zone": "Montagnes des Koalaks",
    "sous-zone": "Cimetière primitif",
    "imgURL": "https://res.cloudinary.com/dinaj1mwf/image/upload/v1683925178/maitre_koalak_unlave.jpg"
  },
  {
    "nom": "Onabuémangé la Rassasiée",
    "etape": 33,
    "zone": "Île de Grobe",
    "sous-zone": "Cimetière de Grobe",
    "imgURL": "https://res.cloudinary.com/dinaj1mwf/image/upload/v1683925157/onabu-geisha_xd6qkg.png"
  },
  {
    "nom": "Poolopo la Traditionnelle",
    "etape": 33,
    "zone": "Île d'Otomaï",
    "sous-zone": "Tronc de l'Arbre Hakam",
    "imgURL": "https://res.cloudinary.com/dinaj1mwf/image/upload/v1683925159/poolay_oq2bw9.jpg"
  },
  {
    "nom": "Seripoth l'Ennemi",
    "etape": 33,
    "zone": "Île d'Otomaï",
    "sous-zone": "Village de la Canopée",
    "imgURL": "https://res.cloudinary.com/dinaj1mwf/image/upload/v1683925161/sergent_zoth_kx8sgk.jpg"
  },
  {
    "nom": "Tambouille le Gastronome",
    "etape": 33,
    "zone": "Île de Grobe",
    "sous-zone": "Cimetière de Grobe",
    "imgURL": "https://res.cloudinary.com/dinaj1mwf/image/upload/v1683925161/tambourai_vwj1qy.png"
  },
  {
    "nom": "Toutouf le Velu",
    "etape": 33,
    "zone": "Île d'Otomaï",
    "sous-zone": "Tronc de l'Arbre Hakam",
    "imgURL": "https://res.cloudinary.com/dinaj1mwf/image/upload/v1683925165/bitouf_aerien_lmfvzq.jpg"
  },
  {
    "nom": "Tromplamor le Survivant",
    "etape": 33,
    "zone": "Landes de Sidimote",
    "sous-zone": "Domaine des Fungus",
    "imgURL": "https://res.cloudinary.com/dinaj1mwf/image/upload/v1683925162/tromperelle_dnybeh.jpg"
  },
  {
    "nom": "Trooyé l'Oxydé",
    "etape": 33,
    "zone": "Plaines de Cania",
    "sous-zone": "Bois de Litneg",
    "imgURL": "https://res.cloudinary.com/dinaj1mwf/image/upload/v1683925162/trooll_gge819.jpg"
  },
  {
    "nom": "Tsucékoi la Colporteuse",
    "etape": 33,
    "zone": "Île de Grobe",
    "sous-zone": "Cimetière de Grobe",
    "imgURL": "https://res.cloudinary.com/dinaj1mwf/image/upload/v1683925162/tsukinochi_qska0n.png"
  },
  {
    "nom": "Bakaglace le Congelé",
    "etape": 34,
    "zone": "Île de Grobe",
    "sous-zone": "Mont des Tombeaux",
    "imgURL": "https://res.cloudinary.com/dinaj1mwf/image/upload/v1683925164/bakazako_dk6pgw.png"
  },
  {
    "nom": "Kaonucléair l'Instable",
    "etape": 34,
    "zone": "Île de Grobe",
    "sous-zone": "Mont des Tombeaux",
    "imgURL": "https://res.cloudinary.com/dinaj1mwf/image/upload/v1683925175/kaonashi_sqsb9c.png"
  },
  {
    "nom": "Madgang le Docteur",
    "etape": 34,
    "zone": "Île de Grobe",
    "sous-zone": "Mont des Tombeaux",
    "imgURL": "https://res.cloudinary.com/dinaj1mwf/image/upload/v1683925178/madura_wdmuyp.png"
  },
  {
    "nom": "Roy le Merlin",
    "etape": 34,
    "zone": "Île d'Otomaï",
    "sous-zone": "Tourbière sans fond",
    "imgURL": "https://res.cloudinary.com/dinaj1mwf/image/upload/v1683925160/roissingue_uegmmy.jpg"
  },
  {
    "nom": "Tronquette la Réduite",
    "etape": 34,
    "zone": "Île de Pandala",
    "sous-zone": "Feudala",
    "imgURL": "https://res.cloudinary.com/dinaj1mwf/image/upload/v1683925160/rouquette_z6ylcs.png"
  },
  {
    "nom": "Tsumani l'Inondeur",
    "etape": 34,
    "zone": "Île de Grobe",
    "sous-zone": "Mont des Tombeaux",
    "imgURL": "https://res.cloudinary.com/dinaj1mwf/image/upload/v1683925162/tsume-bozu_pcjlyl.png"
  }
]
